simplicial_test/Test.py
simplicial_test/__init__.py
simplicial_test/custom_exceptions.py
simplicial_test/draw.py
simplicial_test/enumeration.py
simplicial_test/sample.py
simplicial_test/utils.py
simplicial_test/validators.py
tests/__init__.py
tests/test_batch.py
tests/test_empirical_data.py
tests/test_not_simplicial.py
tests/test_simplicial.py
simplicial_test-1.3.0.dist-info/COPYING
simplicial_test-1.3.0.dist-info/COPYING.LESSER
simplicial_test-1.3.0.dist-info/METADATA
simplicial_test-1.3.0.dist-info/WHEEL
simplicial_test-1.3.0.dist-info/top_level.txt
simplicial_test-1.3.0.dist-info/RECORD
